<annotation>
  <folder>1</folder>
  <filename>ori_XYGOC20200611124751320-4_0.jpg</filename>
  <source>
    <database>CKdemo</database>
    <annotation>VOC</annotation>
    <image>CK</image>
  </source>
  <size>
    <width>960</width>
    <height>720</height>
    <depth>3</depth>
  </size>
  <segmented>0</segmented>
  <object>
    <name>kafei</name>
    <pose/>
    <truncated>0</truncated>
    <difficult>0</difficult>
    <bndbox>
      <xmin>567</xmin>
      <ymin>179</ymin>
      <xmax>666</xmax>
      <ymax>277</ymax>
    </bndbox>
  </object>
  <object>
    <name>kafei</name>
    <pose/>
    <truncated>0</truncated>
    <difficult>0</difficult>
    <bndbox>
      <xmin>316</xmin>
      <ymin>428</ymin>
      <xmax>409</xmax>
      <ymax>522</ymax>
    </bndbox>
  </object>
  <object>
    <name>kafei</name>
    <pose/>
    <truncated>0</truncated>
    <difficult>0</difficult>
    <bndbox>
      <xmin>572</xmin>
      <ymin>426</ymin>
      <xmax>665</xmax>
      <ymax>519</ymax>
    </bndbox>
  </object>
  <object>
    <name>kafei</name>
    <pose/>
    <truncated>0</truncated>
    <difficult>0</difficult>
    <bndbox>
      <xmin>454</xmin>
      <ymin>309</ymin>
      <xmax>530</xmax>
      <ymax>382</ymax>
    </bndbox>
  </object>
  <object>
    <name>kafei</name>
    <pose/>
    <truncated>0</truncated>
    <difficult>0</difficult>
    <bndbox>
      <xmin>472</xmin>
      <ymin>82</ymin>
      <xmax>537</xmax>
      <ymax>187</ymax>
    </bndbox>
  </object>
  <object>
    <name>kafei</name>
    <pose/>
    <truncated>0</truncated>
    <difficult>0</difficult>
    <bndbox>
      <xmin>703</xmin>
      <ymin>390</ymin>
      <xmax>793</xmax>
      <ymax>452</ymax>
    </bndbox>
  </object>
  <object>
    <name>kafei</name>
    <pose/>
    <truncated>0</truncated>
    <difficult>0</difficult>
    <bndbox>
      <xmin>670</xmin>
      <ymin>489</ymin>
      <xmax>757</xmax>
      <ymax>562</ymax>
    </bndbox>
  </object>
  <object>
    <name>kafei</name>
    <pose/>
    <truncated>0</truncated>
    <difficult>0</difficult>
    <bndbox>
      <xmin>228</xmin>
      <ymin>125</ymin>
      <xmax>307</xmax>
      <ymax>201</ymax>
    </bndbox>
  </object>
  <object>
    <name>kafei</name>
    <pose/>
    <truncated>0</truncated>
    <difficult>0</difficult>
    <bndbox>
      <xmin>184</xmin>
      <ymin>319</ymin>
      <xmax>275</xmax>
      <ymax>379</ymax>
    </bndbox>
  </object>
  <object>
    <name>kafei</name>
    <pose/>
    <truncated>0</truncated>
    <difficult>0</difficult>
    <bndbox>
      <xmin>222</xmin>
      <ymin>487</ymin>
      <xmax>308</xmax>
      <ymax>558</ymax>
    </bndbox>
  </object>
  <object>
    <name>kafei</name>
    <pose/>
    <truncated>0</truncated>
    <difficult>0</difficult>
    <bndbox>
      <xmin>678</xmin>
      <ymin>130</ymin>
      <xmax>761</xmax>
      <ymax>204</ymax>
    </bndbox>
  </object>
  <object>
    <name>kafei</name>
    <pose/>
    <truncated>0</truncated>
    <difficult>0</difficult>
    <bndbox>
      <xmin>453</xmin>
      <ymin>500</ymin>
      <xmax>515</xmax>
      <ymax>603</ymax>
    </bndbox>
  </object>
  <object>
    <name>kafei</name>
    <pose/>
    <truncated>0</truncated>
    <difficult>0</difficult>
    <bndbox>
      <xmin>347</xmin>
      <ymin>178</ymin>
      <xmax>442</xmax>
      <ymax>277</ymax>
    </bndbox>
  </object>
  <object>
    <name>kafei</name>
    <pose/>
    <truncated>0</truncated>
    <difficult>0</difficult>
    <bndbox>
      <xmin>703</xmin>
      <ymin>260</ymin>
      <xmax>796</xmax>
      <ymax>325</ymax>
    </bndbox>
  </object>
</annotation>
