<annotation>
  <folder>1</folder>
  <filename>ori_XYGOC2021042210532260901IK-3_0.jpg</filename>
  <source>
    <database>CKdemo</database>
    <annotation>VOC</annotation>
    <image>CK</image>
  </source>
  <size>
    <width>960</width>
    <height>720</height>
    <depth>3</depth>
  </size>
  <segmented>0</segmented>
  <object>
    <name>chapai2</name>
    <pose/>
    <truncated>0</truncated>
    <difficult>0</difficult>
    <bndbox>
      <xmin>72</xmin>
      <ymin>273</ymin>
      <xmax>155</xmax>
      <ymax>384</ymax>
    </bndbox>
  </object>
</annotation>
