<annotation>
  <folder>1</folder>
  <filename>ori_XYGOC2021010413541633401IK-3_0.jpg</filename>
  <source>
    <database>CKdemo</database>
    <annotation>VOC</annotation>
    <image>CK</image>
  </source>
  <size>
    <width>960</width>
    <height>720</height>
    <depth>3</depth>
  </size>
  <segmented>0</segmented>
  <object>
    <name>jianlibao</name>
    <pose/>
    <truncated>0</truncated>
    <difficult>0</difficult>
    <bndbox>
      <xmin>258</xmin>
      <ymin>496</ymin>
      <xmax>382</xmax>
      <ymax>609</ymax>
    </bndbox>
  </object>
  <object>
    <name>jianlibao</name>
    <pose/>
    <truncated>0</truncated>
    <difficult>0</difficult>
    <bndbox>
      <xmin>302</xmin>
      <ymin>603</ymin>
      <xmax>405</xmax>
      <ymax>668</ymax>
    </bndbox>
  </object>
  <object>
    <name>mangguoxiaolao</name>
    <pose/>
    <truncated>0</truncated>
    <difficult>0</difficult>
    <bndbox>
      <xmin>188</xmin>
      <ymin>472</ymin>
      <xmax>264</xmax>
      <ymax>568</ymax>
    </bndbox>
  </object>
  <object>
    <name>jianlibao</name>
    <pose/>
    <truncated>0</truncated>
    <difficult>0</difficult>
    <bndbox>
      <xmin>228</xmin>
      <ymin>348</ymin>
      <xmax>361</xmax>
      <ymax>498</ymax>
    </bndbox>
  </object>
  <object>
    <name>mangguoxiaolao</name>
    <pose/>
    <truncated>0</truncated>
    <difficult>0</difficult>
    <bndbox>
      <xmin>223</xmin>
      <ymin>566</ymin>
      <xmax>302</xmax>
      <ymax>636</ymax>
    </bndbox>
  </object>
  <object>
    <name>mangguoxiaolao</name>
    <pose/>
    <truncated>0</truncated>
    <difficult>0</difficult>
    <bndbox>
      <xmin>171</xmin>
      <ymin>349</ymin>
      <xmax>237</xmax>
      <ymax>469</ymax>
    </bndbox>
  </object>
</annotation>
