<annotation>
  <folder>1</folder>
  <filename>ori_XYGOC20200611112455387-3_0.jpg</filename>
  <source>
    <database>CKdemo</database>
    <annotation>VOC</annotation>
    <image>CK</image>
  </source>
  <size>
    <width>960</width>
    <height>720</height>
    <depth>3</depth>
  </size>
  <segmented>0</segmented>
  <object>
    <name>lingdukele</name>
    <pose/>
    <truncated>0</truncated>
    <difficult>0</difficult>
    <bndbox>
      <xmin>797</xmin>
      <ymin>403</ymin>
      <xmax>865</xmax>
      <ymax>497</ymax>
    </bndbox>
  </object>
  <object>
    <name>kafei</name>
    <pose/>
    <truncated>0</truncated>
    <difficult>0</difficult>
    <bndbox>
      <xmin>195</xmin>
      <ymin>182</ymin>
      <xmax>421</xmax>
      <ymax>378</ymax>
    </bndbox>
  </object>
  <object>
    <name>lingdukele</name>
    <pose/>
    <truncated>0</truncated>
    <difficult>0</difficult>
    <bndbox>
      <xmin>750</xmin>
      <ymin>112</ymin>
      <xmax>820</xmax>
      <ymax>202</ymax>
    </bndbox>
  </object>
  <object>
    <name>lingdukele</name>
    <pose/>
    <truncated>0</truncated>
    <difficult>0</difficult>
    <bndbox>
      <xmin>799</xmin>
      <ymin>240</ymin>
      <xmax>865</xmax>
      <ymax>337</ymax>
    </bndbox>
  </object>
  <object>
    <name>kafei</name>
    <pose/>
    <truncated>0</truncated>
    <difficult>0</difficult>
    <bndbox>
      <xmin>262</xmin>
      <ymin>507</ymin>
      <xmax>417</xmax>
      <ymax>680</ymax>
    </bndbox>
  </object>
  <object>
    <name>lingdukele</name>
    <pose/>
    <truncated>0</truncated>
    <difficult>0</difficult>
    <bndbox>
      <xmin>522</xmin>
      <ymin>38</ymin>
      <xmax>661</xmax>
      <ymax>139</ymax>
    </bndbox>
  </object>
  <object>
    <name>lingdukele</name>
    <pose/>
    <truncated>0</truncated>
    <difficult>0</difficult>
    <bndbox>
      <xmin>527</xmin>
      <ymin>189</ymin>
      <xmax>733</xmax>
      <ymax>412</ymax>
    </bndbox>
  </object>
  <object>
    <name>kafei</name>
    <pose/>
    <truncated>0</truncated>
    <difficult>0</difficult>
    <bndbox>
      <xmin>141</xmin>
      <ymin>533</ymin>
      <xmax>224</xmax>
      <ymax>619</ymax>
    </bndbox>
  </object>
  <object>
    <name>lingdukele</name>
    <pose/>
    <truncated>0</truncated>
    <difficult>0</difficult>
    <bndbox>
      <xmin>756</xmin>
      <ymin>529</ymin>
      <xmax>826</xmax>
      <ymax>611</ymax>
    </bndbox>
  </object>
  <object>
    <name>kafei</name>
    <pose/>
    <truncated>0</truncated>
    <difficult>0</difficult>
    <bndbox>
      <xmin>341</xmin>
      <ymin>8</ymin>
      <xmax>462</xmax>
      <ymax>155</ymax>
    </bndbox>
  </object>
  <object>
    <name>kafei</name>
    <pose/>
    <truncated>0</truncated>
    <difficult>0</difficult>
    <bndbox>
      <xmin>156</xmin>
      <ymin>96</ymin>
      <xmax>246</xmax>
      <ymax>180</ymax>
    </bndbox>
  </object>
  <object>
    <name>lingdukele</name>
    <pose/>
    <truncated>0</truncated>
    <difficult>0</difficult>
    <bndbox>
      <xmin>514</xmin>
      <ymin>551</ymin>
      <xmax>675</xmax>
      <ymax>676</ymax>
    </bndbox>
  </object>
  <object>
    <name>kafei</name>
    <pose/>
    <truncated>0</truncated>
    <difficult>0</difficult>
    <bndbox>
      <xmin>85</xmin>
      <ymin>373</ymin>
      <xmax>186</xmax>
      <ymax>456</ymax>
    </bndbox>
  </object>
  <object>
    <name>kafei</name>
    <pose/>
    <truncated>0</truncated>
    <difficult>0</difficult>
    <bndbox>
      <xmin>96</xmin>
      <ymin>218</ymin>
      <xmax>201</xmax>
      <ymax>314</ymax>
    </bndbox>
  </object>
</annotation>
